naps_utilities/__init__.py
naps_utilities/conversion.py
naps_utilities/pointcloud.py
naps_utilities/tranform.py
naps_utilities/transform.py
naps_utilities-0.3.2.dist-info/METADATA
naps_utilities-0.3.2.dist-info/WHEEL
naps_utilities-0.3.2.dist-info/top_level.txt
naps_utilities-0.3.2.dist-info/RECORD
