Metadata-Version: 2.1
Name: naps-utilities
Version: 0.3.2
Summary: Lib to handle ease of use of pointclouds 
Home-page: https://github.com/virgileTN/naps_utilities
Author: Virgile Daugé
Author-email: virgile.dauge@loria.fr
License: UNKNOWN
Keywords: pointclouds,filtering
Platform: UNKNOWN
Classifier: Development Status :: 4 - Beta
Classifier: Environment :: Console
Classifier: Intended Audience :: Developers
Classifier: License :: OSI Approved :: GNU General Public License (GPL)
Classifier: Operating System :: MacOS :: MacOS X
Classifier: Operating System :: POSIX
Classifier: Programming Language :: Python :: 3.6
Requires-Dist: numpy
Requires-Dist: numpy-quaternion
